[
  {
            "src":"images/image01.jpg",
            "title":"Image1"

  },

  {
            "src":"images/image02.jpg",
            "title":"Image2"

  },

  {
            "src":"images/image03.jpg",
            "title":"Image3"

  },

  {
            "src":"images/image04.jpg",
            "title":"Image4"

  },


  {
            "src":"images/image05.jpg",
            "title":"Image5"

  },


  {
            "src":"images/image06.jpg",
            "title":"Image6"

  },

  {
            "src":"images/image07.jpg",
            "title":"Image7"

  },
  {
            "src":"images/image08.jpg",
            "title":"Image8"

  }

 
 
]